{
	"info": {
		"_postman_id": "d65c9e76-be59-4e0c-91e3-67777cbf66c3",
		"name": "MERN Express",
		"schema": "https://schema.getpostman.com/json/collection/v2.1.0/collection.json",
		"_exporter_id": "20325262"
	},
	"item": [
		{
			"name": "GET",
			"request": {
				"method": "GET",
				"header": [],
				"url": {
					"raw": "http://localhost:4000/api/workouts/",
					"protocol": "http",
					"host": [
						"localhost"
					],
					"port": "4000",
					"path": [
						"api",
						"workouts",
						""
					]
				}
			},
			"response": []
		},
		{
			"name": "GET Single",
			"request": {
				"method": "GET",
				"header": [],
				"url": {
					"raw": "http://localhost/api/workouts/669b82e4775da81cebd84687",
					"protocol": "http",
					"host": [
						"localhost"
					],
					"path": [
						"api",
						"workouts",
						"669b82e4775da81cebd84687"
					]
				}
			},
			"response": []
		},
		{
			"name": "POST",
			"request": {
				"method": "POST",
				"header": [],
				"body": {
					"mode": "raw",
					"raw": "{\r\n    \"title\": \"Push-up\",\r\n    \"load\": 0,\r\n    \"reps\": 10\r\n}",
					"options": {
						"raw": {
							"language": "json"
						}
					}
				},
				"url": {
					"raw": "http://localhost:4000/api/workouts/",
					"protocol": "http",
					"host": [
						"localhost"
					],
					"port": "4000",
					"path": [
						"api",
						"workouts",
						""
					]
				}
			},
			"response": []
		},
		{
			"name": "Update",
			"request": {
				"method": "PATCH",
				"header": [],
				"body": {
					"mode": "raw",
					"raw": "{\r\n    \"title\": \"Jumping\"\r\n}",
					"options": {
						"raw": {
							"language": "json"
						}
					}
				},
				"url": {
					"raw": "http://localhost/api/workouts/669b82e4775da81cebd84687",
					"protocol": "http",
					"host": [
						"localhost"
					],
					"path": [
						"api",
						"workouts",
						"669b82e4775da81cebd84687"
					]
				}
			},
			"response": []
		},
		{
			"name": "Delete",
			"request": {
				"method": "DELETE",
				"header": [],
				"url": {
					"raw": "http://localhost:4000/api/workouts/669b995e53195ce86af75154",
					"protocol": "http",
					"host": [
						"localhost"
					],
					"port": "4000",
					"path": [
						"api",
						"workouts",
						"669b995e53195ce86af75154"
					]
				}
			},
			"response": []
		}
	]
}